whist/__init__.py
whist/cards.py
whist/game.py
whist/game_actions.py
whist/game_ai.py
whist/game_events.py
whist/gamestate.py
whist/partners.py
whist/player.py
whist-0.1.0.dist-info/LICENSE
whist-0.1.0.dist-info/METADATA
whist-0.1.0.dist-info/WHEEL
whist-0.1.0.dist-info/top_level.txt
whist-0.1.0.dist-info/RECORD
