Metadata-Version: 2.1
Name: whist
Version: 0.1.0
Summary: A package containing the logic for the card game Whist and its variants.
Home-page: https://github.com/PeterSR/pywhist
Author: Peter Severin Rasmussen
Author-email: git@petersr.com
License: MIT License
Platform: UNKNOWN
Requires-Python: >=3.7
